{
	"EngineVersions": [
		{
			"Version": 1.0000,
			"VersionFriendly": "Midnight - 1.00.00 (No TU)",
			"QuickOptions": [
				{
					"Name": "Toggle Debug Camera",
					"Description": "Toggles the visibility of the Debug Camera Coordinates.",
					"Address": 2184070411,
					"IsToggle": true,
					"IconResourceKey": "MemoryIconDebugCameraTemplate"
				},
				{
					"Name": "Redraw Shaders",
					"Description": "Redraws the cache's shaders, without reloading the map.",
					"Address": 2215115607,
					"IconResourceKey": "MemoryIconRedrawShadersTemplate"
				},
				{
					"Name": "Create Checkpoint",
					"Description": "Creates a gamestate checkpoint in the engine.",
					"Address": 2216755446,
					"IconResourceKey": "MemoryIconCreateCheckpointTemplate"
				},
				{
					"Name": "Load Checkpoint",
					"Description": "Loads the most recent gamestate checkpoint (if no checkpoint has been set in a multiplayer match, it will reload the scenario).",
					"Address": 2216755442,
					"IconResourceKey": "MemoryIconRevertCheckpointTemplate"
				},
				{
					"Name": "Reload Cache",
					"Description": "Reloads the current cache.",
					"Address": 2217108407,
					"IconResourceKey": "MemoryIconReloadCacheTemplate"
				},
				{
					"Name": "End Game",
					"Description": "Ends the current game, careful guys.",
					"Address": 2216755447,
					"CarefulMode": true,
					"IconResourceKey": "MemoryIconEndGameTemplate"
				}
			],
			"MemoryValues": [
				{
					"Name": "Toggle Debug Camera", 
					"Description": "Toggles the visibility of the Debug Camera Coordinates. (0x01 = on, 0x00 = off)", 
					"Address": 2184070411, 
					"Type": "byte", 
					"Data": "01"
				},
				{
					"Name": "Redraw Shaders", 
					"Description": "Redraws the cache's shaders, without reloading the map.", 
					"Address": 2215115607, 
					"Type": "byte", 
					"Data": "01"
				},
				{
					"Name": "Create Checkpoint", 
					"Description": "Creates a gamestate checkpoint in the engine.", 
					"Address": 2216755446, 
					"Type": "byte", 
					"Data": "01"
				},
				{
					"Name": "Load Checkpoint", 
					"Description": "Loads the most recent gamestate checkpoint (if no checkpoint has been set in a multiplayer match, it will reload the scenario).", 
					"Address": 2216755442, 
					"Type": "byte", 
					"Data": "01"
				},
				{
					"Name": "Reload Cache", 
					"Description": "Reloads the current cache.", 
					"Address": 2217108407, 
					"Type": "byte", 
					"Data": "01"
				},
				{
					"Name": "End Game", 
					"Description": "Ends the current game, careful guys.", 
					"Address": 2216755447, 
					"Type": "byte", 
					"Data": "01"
				},
				{
					"Name": "Gravity", 
					"Description": "Sets the global gravity. Takes effect on map reload.", 
					"Address": 2182253768, 
					"Type": "float", 
					"Data": "4.1712594"
				},
				{
					"Name": "Third Person", 
					"Description": "Globally sets the player's perspective to third person.", 
					"Address": 2185735764, 
					"Type": "bytes", 
					"Data": "60000000"
				},
				{
					"Name": "Allow Campaign Films", 
					"Description": "Removes checks of the engine to allow films. Poke in lobby; poke back to 00 before ending the game.", 
					"Address": 2189311283, 
					"Type": "bytes", 
					"Data": "01"
				},
				{
					"Name": "Unlock Campaign", 
					"Description": "Unlocks all campaign missions and insertion points.", 
					"Address": 3262446290, 
					"Type": "bytes", 
					"Data": "FFFFFFFFFFFFFFFFFFFFFFFFFFFFFFFFFFFFFFFFFFFFFFFFFFFFFFFFFFFF"
				}
			]
		},
		{
			"Version": 1.0100,
			"VersionFriendly": "Midnight - 1.01.00 (TU 1)",
			"QuickOptions": [
				{
					"Name": "Toggle Debug Camera",
					"Description": "Toggles the visibility of the Debug Camera Coordinates.",
					"Address": 2184071723,
					"IsToggle": true,
					"IconResourceKey": "MemoryIconDebugCameraTemplate"
				},
				{
					"Name": "Redraw Shaders",
					"Description": "Redraws the cache's shaders, without reloading the map.",
					"Address": 2215116272,
					"IconResourceKey": "MemoryIconRedrawShadersTemplate"
				},
				{
					"Name": "Create Checkpoint",
					"Description": "Creates a gamestate checkpoint in the engine.",
					"Address": 2216755958,
					"IconResourceKey": "MemoryIconCreateCheckpointTemplate"
				},
				{
					"Name": "Load Checkpoint",
					"Description": "Loads the most recent gamestate checkpoint (if no checkpoint has been set in a multiplayer match, it will reload the scenario).",
					"Address": 2216755954,
					"IconResourceKey": "MemoryIconRevertCheckpointTemplate"
				},
				{
					"Name": "Reload Cache",
					"Description": "Reloads the current cache.",
					"Address": 2217119447,
					"IconResourceKey": "MemoryIconReloadCacheTemplate"
				},
				{
					"Name": "End Game",
					"Description": "Ends the current game, careful guys.",
					"Address": 2216755959,
					"CarefulMode": true,
					"IconResourceKey": "MemoryIconEndGameTemplate"
				}
			],
			"MemoryValues": [
				{
					"Name": "Toggle Debug Camera", 
					"Description": "Toggles the visibility of the Debug Camera Coordinates. (0x01 = on, 0x00 = off)", 
					"Address": 2184071723, 
					"Type": "byte", 
					"Data": "01"
				},
				{
					"Name": "Redraw Shaders", 
					"Description": "Redraws the cache's shaders, without reloading the map.", 
					"Address": 2215116272, 
					"Type": "byte", 
					"Data": "01"
				},
				{
					"Name": "Create Checkpoint", 
					"Description": "Creates a gamestate checkpoint in the engine.", 
					"Address": 2216755958, 
					"Type": "byte", 
					"Data": "01"
				},
				{
					"Name": "Load Checkpoint", 
					"Description": "Loads the most recent gamestate checkpoint (if no checkpoint has been set in a multiplayer match, it will reload the scenario).", 
					"Address": 2216755954, 
					"Type": "byte", 
					"Data": "01"
				},
				{
					"Name": "Reload Cache", 
					"Description": "Reloads the current cache.", 
					"Address": 2217119447, 
					"Type": "byte", 
					"Data": "01"
				},
				{
					"Name": "End Game", 
					"Description": "Ends the current game, careful guys.", 
					"Address": 2216755959, 
					"Type": "byte", 
					"Data": "01"
				},
				{
					"Name": "Gravity", 
					"Description": "Sets the global gravity. Takes effect on map reload.", 
					"Address": 2182254300, 
					"Type": "float", 
					"Data": "4.1712594"
				},
				{
					"Name": "Third Person", 
					"Description": "Globally sets the player's perspective to third person.", 
					"Address": 2185736412, 
					"Type": "bytes", 
					"Data": "60000000"
				},
				{
					"Name": "Allow Campaign Films", 
					"Description": "Removes checks of the engine to allow films. Poke in lobby; poke back to 00 before ending the game.", 
					"Address": 2189313667, 
					"Type": "bytes", 
					"Data": "01"
				},
				{
					"Name": "Unlock Campaign", 
					"Description": "Unlocks all campaign missions and insertion points.", 
					"Address": 3262512346, 
					"Type": "bytes", 
					"Data": "FFFFFFFFFFFFFFFFFFFFFFFFFFFFFFFFFFFFFFFFFFFFFFFFFFFFFFFFFFFF"
				}
			]
		},
		{
			"Version": 1.0200,
			"VersionFriendly": "Midnight - 1.02.00 (TU 2)",
			"QuickOptions": [
				{
					"Name": "Toggle Debug Camera",
					"Description": "Toggles the visibility of the Debug Camera Coordinates.",
					"Address": 2184070675,
					"IsToggle": true,
					"IconResourceKey": "MemoryIconDebugCameraTemplate"
				},
				{
					"Name": "Redraw Shaders",
					"Description": "Redraws the cache's shaders, without reloading the map.",
					"Address": 2215116258,
					"IconResourceKey": "MemoryIconRedrawShadersTemplate"
				},
				{
					"Name": "Create Checkpoint",
					"Description": "Creates a gamestate checkpoint in the engine.",
					"Address": 2216754918,
					"IconResourceKey": "MemoryIconCreateCheckpointTemplate"
				},
				{
					"Name": "Load Checkpoint",
					"Description": "Loads the most recent gamestate checkpoint (if no checkpoint has been set in a multiplayer match, it will reload the scenario).",
					"Address": 2216754914,
					"IconResourceKey": "MemoryIconRevertCheckpointTemplate"
				},
				{
					"Name": "Reload Cache",
					"Description": "Reloads the current cache.",
					"Address": 2217118391,
					"IconResourceKey": "MemoryIconReloadCacheTemplate"
				},
				{
					"Name": "End Game",
					"Description": "Ends the current game, careful guys.",
					"Address": 2216754919,
					"CarefulMode": true,
					"IconResourceKey": "MemoryIconEndGameTemplate"
				}
			],
			"MemoryValues": [
				{
					"Name": "Toggle Debug Camera", 
					"Description": "Toggles the visibility of the Debug Camera Coordinates. (0x01 = on, 0x00 = off)", 
					"Address": 2184070675, 
					"Type": "byte", 
					"Data": "01"
				},
				{
					"Name": "Redraw Shaders", 
					"Description": "Redraws the cache's shaders, without reloading the map.", 
					"Address": 2215116258, 
					"Type": "byte", 
					"Data": "01"
				},
				{
					"Name": "Create Checkpoint", 
					"Description": "Creates a gamestate checkpoint in the engine.", 
					"Address": 2216754918, 
					"Type": "byte", 
					"Data": "01"
				},
				{
					"Name": "Load Checkpoint", 
					"Description": "Loads the most recent gamestate checkpoint (if no checkpoint has been set in a multiplayer match, it will reload the scenario).", 
					"Address": 2216754914, 
					"Type": "byte", 
					"Data": "01"
				},
				{
					"Name": "Reload Cache", 
					"Description": "Reloads the current cache.", 
					"Address": 2217118391, 
					"Type": "byte", 
					"Data": "01"
				},
				{
					"Name": "End Game", 
					"Description": "Ends the current game, careful guys.", 
					"Address": 2216754919, 
					"Type": "byte", 
					"Data": "01"
				},
				{
					"Name": "Gravity", 
					"Description": "Sets the global gravity. Takes effect on map reload.", 
					"Address": 2182255116, 
					"Type": "float", 
					"Data": "4.1712594"
				},
				{
					"Name": "Third Person", 
					"Description": "Globally sets the player's perspective to third person.", 
					"Address": 2185741628, 
					"Type": "bytes", 
					"Data": "60000000"
				},
				{
					"Name": "Allow Campaign Films", 
					"Description": "Removes checks of the engine to allow films. Poke in lobby; poke back to 00 before ending the game.", 
					"Address": 2189321019, 
					"Type": "bytes", 
					"Data": "01"
				},
				{
					"Name": "Unlock Campaign", 
					"Description": "Unlocks all campaign missions and insertion points.", 
					"Address": 3262449882, 
					"Type": "bytes", 
					"Data": "FFFFFFFFFFFFFFFFFFFFFFFFFFFFFFFFFFFFFFFFFFFFFFFFFFFFFFFFFFFF"
				}
			]
		},
		{
			"Version": 1.0201,
			"VersionFriendly": "Midnight - 1.02.01 (TU 3)",
			"QuickOptions": [
				{
					"Name": "Toggle Debug Camera",
					"Description": "Toggles the visibility of the Debug Camera Coordinates.",
					"Address": 2184070539,
					"IsToggle": true,
					"IconResourceKey": "MemoryIconDebugCameraTemplate"
				},
				{
					"Name": "Redraw Shaders",
					"Description": "Redraws the cache's shaders, without reloading the map.",
					"Address": 2215116258,
					"IconResourceKey": "MemoryIconRedrawShadersTemplate"
				},
				{
					"Name": "Create Checkpoint",
					"Description": "Creates a gamestate checkpoint in the engine.",
					"Address": 2216754918,
					"IconResourceKey": "MemoryIconCreateCheckpointTemplate"
				},
				{
					"Name": "Load Checkpoint",
					"Description": "Loads the most recent gamestate checkpoint (if no checkpoint has been set in a multiplayer match, it will reload the scenario).",
					"Address": 2216754914,
					"IconResourceKey": "MemoryIconRevertCheckpointTemplate"
				},
				{
					"Name": "Reload Cache",
					"Description": "Reloads the current cache.",
					"Address": 2217118391,
					"IconResourceKey": "MemoryIconReloadCacheTemplate"
				},
				{
					"Name": "End Game",
					"Description": "Ends the current game, careful guys.",
					"Address": 2216754919,
					"CarefulMode": true,
					"IconResourceKey": "MemoryIconEndGameTemplate"
				}
			],
			"MemoryValues": [
				{
					"Name": "Toggle Debug Camera", 
					"Description": "Toggles the visibility of the Debug Camera Coordinates. (0x01 = on, 0x00 = off)", 
					"Address": 2184070539, 
					"Type": "byte", 
					"Data": "01"
				},
				{
					"Name": "Redraw Shaders", 
					"Description": "Redraws the cache's shaders, without reloading the map.", 
					"Address": 2215116258, 
					"Type": "byte", 
					"Data": "01"
				},
				{
					"Name": "Create Checkpoint", 
					"Description": "Creates a gamestate checkpoint in the engine.", 
					"Address": 2216754918, 
					"Type": "byte", 
					"Data": "01"
				},
				{
					"Name": "Load Checkpoint", 
					"Description": "Loads the most recent gamestate checkpoint (if no checkpoint has been set in a multiplayer match, it will reload the scenario).", 
					"Address": 2216754914, 
					"Type": "byte", 
					"Data": "01"
				},
				{
					"Name": "Reload Cache", 
					"Description": "Reloads the current cache.", 
					"Address": 2217118391, 
					"Type": "byte", 
					"Data": "01"
				},
				{
					"Name": "End Game", 
					"Description": "Ends the current game, careful guys.", 
					"Address": 2216754919, 
					"Type": "byte", 
					"Data": "01"
				},
				{
					"Name": "Gravity", 
					"Description": "Sets the global gravity. Takes effect on map reload.", 
					"Address": 2182255116, 
					"Type": "float", 
					"Data": "4.1712594"
				},
				{
					"Name": "Third Person", 
					"Description": "Globally sets the player's perspective to third person.", 
					"Address": 2185740444, 
					"Type": "bytes", 
					"Data": "60000000"
				},
				{
					"Name": "Allow Campaign Films", 
					"Description": "Removes checks of the engine to allow films. Poke in lobby; poke back to 00 before ending the game.", 
					"Address": 2189320499, 
					"Type": "bytes", 
					"Data": "01"
				},
				{
					"Name": "Unlock Campaign", 
					"Description": "Unlocks all campaign missions and insertion points.", 
					"Address": 3262449882, 
					"Type": "bytes", 
					"Data": "FFFFFFFFFFFFFFFFFFFFFFFFFFFFFFFFFFFFFFFFFFFFFFFFFFFFFFFFFFFF"
				}
			]
		},
		{
			"Version": 1.0300,
			"VersionFriendly": "Midnight - 1.03.00 (TU 4)",
			"QuickOptions": [
				{
					"Name": "Toggle Debug Camera",
					"Description": "Toggles the visibility of the Debug Camera Coordinates.",
					"Address": 2184070883,
					"IsToggle": true,
					"IconResourceKey": "MemoryIconDebugCameraTemplate"
				},
				{
					"Name": "Redraw Shaders",
					"Description": "Redraws the cache's shaders, without reloading the map.",
					"Address": 2215182566,
					"IconResourceKey": "MemoryIconRedrawShadersTemplate"
				},
				{
					"Name": "Create Checkpoint",
					"Description": "Creates a gamestate checkpoint in the engine.",
					"Address": 2216821350,
					"IconResourceKey": "MemoryIconCreateCheckpointTemplate"
				},
				{
					"Name": "Load Checkpoint",
					"Description": "Loads the most recent gamestate checkpoint (if no checkpoint has been set in a multiplayer match, it will reload the scenario).",
					"Address": 2216821346,
					"IconResourceKey": "MemoryIconRevertCheckpointTemplate"
				},
				{
					"Name": "Reload Cache",
					"Description": "Reloads the current cache.",
					"Address": 2217184991,
					"IconResourceKey": "MemoryIconReloadCacheTemplate"
				},
				{
					"Name": "End Game",
					"Description": "Ends the current game, careful guys.",
					"Address": 2216821351,
					"CarefulMode": true,
					"IconResourceKey": "MemoryIconEndGameTemplate"
				}
			],
			"MemoryValues": [
				{
					"Name": "Toggle Debug Camera", 
					"Description": "Toggles the visibility of the Debug Camera Coordinates. (0x01 = on, 0x00 = off)", 
					"Address": 2184070883, 
					"Type": "byte", 
					"Data": "01"
				},
				{
					"Name": "Redraw Shaders", 
					"Description": "Redraws the cache's shaders, without reloading the map.", 
					"Address": 2215182566, 
					"Type": "byte", 
					"Data": "01"
				},
				{
					"Name": "Create Checkpoint", 
					"Description": "Creates a gamestate checkpoint in the engine.", 
					"Address": 2216821350, 
					"Type": "byte", 
					"Data": "01"
				},
				{
					"Name": "Load Checkpoint", 
					"Description": "Loads the most recent gamestate checkpoint (if no checkpoint has been set in a multiplayer match, it will reload the scenario).", 
					"Address": 2216821346, 
					"Type": "byte", 
					"Data": "01"
				},
				{
					"Name": "Reload Cache", 
					"Description": "Reloads the current cache.", 
					"Address": 2217184991, 
					"Type": "byte", 
					"Data": "01"
				},
				{
					"Name": "End Game", 
					"Description": "Ends the current game, careful guys.", 
					"Address": 2216821351, 
					"Type": "byte", 
					"Data": "01"
				},
				{
					"Name": "Gravity", 
					"Description": "Sets the global gravity. Takes effect on map reload.", 
					"Address": 2182256584, 
					"Type": "float", 
					"Data": "4.1712594"
				},
				{
					"Name": "Third Person", 
					"Description": "Globally sets the player's perspective to third person.", 
					"Address": 2185744348, 
					"Type": "bytes", 
					"Data": "60000000"
				},
				{
					"Name": "Allow Campaign Films", 
					"Description": "Removes checks of the engine to allow films. Poke in lobby; poke back to 00 before ending the game.", 
					"Address": 2189341851, 
					"Type": "bytes", 
					"Data": "01"
				},
				{
					"Name": "Unlock Campaign", 
					"Description": "Unlocks all campaign missions and insertion points.", 
					"Address": 3262583386, 
					"Type": "bytes", 
					"Data": "FFFFFFFFFFFFFFFFFFFFFFFFFFFFFFFFFFFFFFFFFFFFFFFFFFFFFFFFFFFF"
				}
			]
		},
		{
			"Version": 1.0400,
			"VersionFriendly": "Midnight - 1.04.00 (TU 5)",
			"QuickOptions": [
				{
					"Name": "Toggle Debug Camera",
					"Description": "Toggles the visibility of the Debug Camera Coordinates.",
					"Address": 2184137275,
					"IsToggle": true,
					"IconResourceKey": "MemoryIconDebugCameraTemplate"
				},
				{
					"Name": "Redraw Shaders",
					"Description": "Redraws the cache's shaders, without reloading the map.",
					"Address": 2215265006,
					"IconResourceKey": "MemoryIconRedrawShadersTemplate"
				},
				{
					"Name": "Create Checkpoint",
					"Description": "Creates a gamestate checkpoint in the engine.",
					"Address": 2216903782,
					"IconResourceKey": "MemoryIconCreateCheckpointTemplate"
				},
				{
					"Name": "Load Checkpoint",
					"Description": "Loads the most recent gamestate checkpoint (if no checkpoint has been set in a multiplayer match, it will reload the scenario).",
					"Address": 2216903778,
					"IconResourceKey": "MemoryIconRevertCheckpointTemplate"
				},
				{
					"Name": "Reload Cache",
					"Description": "Reloads the current cache.",
					"Address": 2217269343,
					"IconResourceKey": "MemoryIconReloadCacheTemplate"
				},
				{
					"Name": "End Game",
					"Description": "Ends the current game, careful guys.",
					"Address": 2216903783,
					"CarefulMode": true,
					"IconResourceKey": "MemoryIconEndGameTemplate"
				}
			],
			"MemoryValues": [
				{
					"Name": "Toggle Debug Camera", 
					"Description": "Toggles the visibility of the Debug Camera Coordinates. (0x01 = on, 0x00 = off)", 
					"Address": 2184137275, 
					"Type": "byte", 
					"Data": "01"
				},
				{
					"Name": "Redraw Shaders", 
					"Description": "Redraws the cache's shaders, without reloading the map.", 
					"Address": 2215265006, 
					"Type": "byte", 
					"Data": "01"
				},
				{
					"Name": "Create Checkpoint", 
					"Description": "Creates a gamestate checkpoint in the engine.", 
					"Address": 2216903782, 
					"Type": "byte", 
					"Data": "01"
				},
				{
					"Name": "Load Checkpoint", 
					"Description": "Loads the most recent gamestate checkpoint (if no checkpoint has been set in a multiplayer match, it will reload the scenario).", 
					"Address": 2216903778, 
					"Type": "byte", 
					"Data": "01"
				},
				{
					"Name": "Reload Cache", 
					"Description": "Reloads the current cache.", 
					"Address": 2217269343, 
					"Type": "byte", 
					"Data": "01"
				},
				{
					"Name": "End Game", 
					"Description": "Ends the current game, careful guys.", 
					"Address": 2216903783, 
					"Type": "byte", 
					"Data": "01"
				},
				{
					"Name": "Gravity", 
					"Description": "Sets the global gravity. Takes effect on map reload.", 
					"Address": 2182304964, 
					"Type": "float", 
					"Data": "4.1712594"
				},
				{
					"Name": "Third Person", 
					"Description": "Globally sets the player's perspective to third person.", 
					"Address": 2185823172, 
					"Type": "bytes", 
					"Data": "60000000"
				},
				{
					"Name": "Allow Campaign Films", 
					"Description": "Removes checks of the engine to allow films. Poke in lobby; poke back to 00 before ending the game.", 
					"Address": 2189422595, 
					"Type": "bytes", 
					"Data": "01"
				},
				{
					"Name": "Unlock Campaign", 
					"Description": "Unlocks all campaign missions and insertion points.", 
					"Address": 3262805954, 
					"Type": "bytes", 
					"Data": "FFFFFFFFFFFFFFFFFFFFFFFFFFFFFFFFFFFFFFFFFFFFFFFFFFFFFFFFFFFF"
				}
			]
		},
		{
			"Version": 1.0401,
			"VersionFriendly": "Midnight - 1.04.01 (TU 6)",
			"QuickOptions": [
				{
					"Name": "Toggle Debug Camera",
					"Description": "Toggles the visibility of the Debug Camera Coordinates.",
					"Address": 2184136243,
					"IsToggle": true,
					"IconResourceKey": "MemoryIconDebugCameraTemplate"
				},
				{
					"Name": "Redraw Shaders",
					"Description": "Redraws the cache's shaders, without reloading the map.",
					"Address": 2215265390,
					"IconResourceKey": "MemoryIconRedrawShadersTemplate"
				},
				{
					"Name": "Create Checkpoint",
					"Description": "Creates a gamestate checkpoint in the engine.",
					"Address": 2216904166,
					"IconResourceKey": "MemoryIconCreateCheckpointTemplate"
				},
				{
					"Name": "Load Checkpoint",
					"Description": "Loads the most recent gamestate checkpoint (if no checkpoint has been set in a multiplayer match, it will reload the scenario).",
					"Address": 2216904162,
					"IconResourceKey": "MemoryIconRevertCheckpointTemplate"
				},
				{
					"Name": "Reload Cache",
					"Description": "Reloads the current cache.",
					"Address": 2217269887,
					"IconResourceKey": "MemoryIconReloadCacheTemplate"
				},
				{
					"Name": "End Game",
					"Description": "Ends the current game, careful guys.",
					"Address": 2216904167,
					"CarefulMode": true,
					"IconResourceKey": "MemoryIconEndGameTemplate"
				}
			],
			"MemoryValues": [
				{
					"Name": "Toggle Debug Camera", 
					"Description": "Toggles the visibility of the Debug Camera Coordinates. (0x01 = on, 0x00 = off)", 
					"Address": 2184136243, 
					"Type": "byte", 
					"Data": "01"
				},
				{
					"Name": "Redraw Shaders", 
					"Description": "Redraws the cache's shaders, without reloading the map.", 
					"Address": 2215265390, 
					"Type": "byte", 
					"Data": "01"
				},
				{
					"Name": "Create Checkpoint", 
					"Description": "Creates a gamestate checkpoint in the engine.", 
					"Address": 2216904166, 
					"Type": "byte", 
					"Data": "01"
				},
				{
					"Name": "Load Checkpoint", 
					"Description": "Loads the most recent gamestate checkpoint (if no checkpoint has been set in a multiplayer match, it will reload the scenario).", 
					"Address": 2216904162, 
					"Type": "byte", 
					"Data": "01"
				},
				{
					"Name": "Reload Cache", 
					"Description": "Reloads the current cache.", 
					"Address": 2217269887, 
					"Type": "byte", 
					"Data": "01"
				},
				{
					"Name": "End Game", 
					"Description": "Ends the current game, careful guys.", 
					"Address": 2216904167, 
					"Type": "byte", 
					"Data": "01"
				},
				{
					"Name": "Gravity", 
					"Description": "Sets the global gravity. Takes effect on map reload.", 
					"Address": 2182305396, 
					"Type": "float", 
					"Data": "4.1712594"
				},
				{
					"Name": "Third Person", 
					"Description": "Globally sets the player's perspective to third person.", 
					"Address": 2185822380, 
					"Type": "bytes", 
					"Data": "60000000"
				},
				{
					"Name": "Allow Campaign Films", 
					"Description": "Removes checks of the engine to allow films. Poke in lobby; poke back to 00 before ending the game.", 
					"Address": 2189424715, 
					"Type": "bytes", 
					"Data": "01"
				},
				{
					"Name": "Unlock Campaign", 
					"Description": "Unlocks all campaign missions and insertion points.", 
					"Address": 3262937666, 
					"Type": "bytes", 
					"Data": "FFFFFFFFFFFFFFFFFFFFFFFFFFFFFFFFFFFFFFFFFFFFFFFFFFFFFFFFFFFF"
				}
			]
		},
		{
			"Version": 1.0500,
			"VersionFriendly": "Midnight - 1.05.00 (TU 7)",
			"QuickOptions": [
				{
					"Name": "Toggle Debug Camera",
					"Description": "Toggles the visibility of the Debug Camera Coordinates.",
					"Address": 2184138915,
					"IsToggle": true,
					"IconResourceKey": "MemoryIconDebugCameraTemplate"
				},
				{
					"Name": "Redraw Shaders",
					"Description": "Redraws the cache's shaders, without reloading the map.",
					"Address": 2215387542,
					"IconResourceKey": "MemoryIconRedrawShadersTemplate"
				},
				{
					"Name": "Create Checkpoint",
					"Description": "Creates a gamestate checkpoint in the engine.",
					"Address": 2217026278,
					"IconResourceKey": "MemoryIconCreateCheckpointTemplate"
				},
				{
					"Name": "Load Checkpoint",
					"Description": "Loads the most recent gamestate checkpoint (if no checkpoint has been set in a multiplayer match, it will reload the scenario).",
					"Address": 2217026274,
					"IconResourceKey": "MemoryIconRevertCheckpointTemplate"
				},
				{
					"Name": "Reload Cache",
					"Description": "Reloads the current cache.",
					"Address": 2217391999,
					"IconResourceKey": "MemoryIconReloadCacheTemplate"
				},
				{
					"Name": "End Game",
					"Description": "Ends the current game, careful guys.",
					"Address": 2217026279,
					"CarefulMode": true,
					"IconResourceKey": "MemoryIconEndGameTemplate"
				}
			],
			"MemoryValues": [
				{
					"Name": "Toggle Debug Camera", 
					"Description": "Toggles the visibility of the Debug Camera Coordinates. (0x01 = on, 0x00 = off)", 
					"Address": 2184138915, 
					"Type": "byte", 
					"Data": "01"
				},
				{
					"Name": "Redraw Shaders", 
					"Description": "Redraws the cache's shaders, without reloading the map.", 
					"Address": 2215387542, 
					"Type": "byte", 
					"Data": "01"
				},
				{
					"Name": "Create Checkpoint", 
					"Description": "Creates a gamestate checkpoint in the engine.", 
					"Address": 2217026278, 
					"Type": "byte", 
					"Data": "01"
				},
				{
					"Name": "Load Checkpoint", 
					"Description": "Loads the most recent gamestate checkpoint (if no checkpoint has been set in a multiplayer match, it will reload the scenario).", 
					"Address": 2217026274, 
					"Type": "byte", 
					"Data": "01"
				},
				{
					"Name": "Reload Cache", 
					"Description": "Reloads the current cache.", 
					"Address": 2217391999, 
					"Type": "byte", 
					"Data": "01"
				},
				{
					"Name": "End Game", 
					"Description": "Ends the current game, careful guys.", 
					"Address": 2217026279, 
					"Type": "byte", 
					"Data": "01"
				},
				{
					"Name": "Gravity", 
					"Description": "Sets the global gravity. Takes effect on map reload.", 
					"Address": 2182307604, 
					"Type": "float", 
					"Data": "4.1712594"
				},
				{
					"Name": "Third Person", 
					"Description": "Globally sets the player's perspective to third person.", 
					"Address": 2185834684, 
					"Type": "bytes", 
					"Data": "60000000"
				},
				{
					"Name": "Allow Campaign Films", 
					"Description": "Removes checks of the engine to allow films. Poke in lobby; poke back to 00 before ending the game.", 
					"Address": 2189441891, 
					"Type": "bytes", 
					"Data": "01"
				},
				{
					"Name": "Unlock Campaign", 
					"Description": "Unlocks all campaign missions and insertion points.", 
					"Address": 3263061098, 
					"Type": "bytes", 
					"Data": "FFFFFFFFFFFFFFFFFFFFFFFFFFFFFFFFFFFFFFFFFFFFFFFFFFFFFFFFFFFF"
				}
			]
		}
	]
}
