<?xml version="1.0" encoding="utf-8"?>
<plugin game="ReachPreAlpha" baseSize="0x68">
	<!-- Automatically generated plugin -->
	<revisions>
		<revision author="Assembly" version="1">Generated plugin from scratch.</revision>
	</revisions>
	<flags32 name="Flags" offset="0x0" visible="true">
		<bit name="Bit 0" index="0" />
		<bit name="Bit 1" index="1" />
		<bit name="Bit 2" index="2" />
		<bit name="Bit 3" index="3" />
		<bit name="Bit 4" index="4" />
		<bit name="Bit 5" index="5" />
		<bit name="Bit 6" index="6" />
		<bit name="Bit 7" index="7" />
		<bit name="Bit 8" index="8" />
		<bit name="Enable Accelerations?" index="9" />
		<bit name="Dark Casings?" index="10" />
		<bit name="Bit 11" index="11" />
		<bit name="Bit 12" index="12" />
		<bit name="Bit 13" index="13" />
		<bit name="Bit 14" index="14" />
		<bit name="Bit 15" index="15" />
		<bit name="Bit 16" index="16" />
		<bit name="Bit 17" index="17" />
		<bit name="Bit 18" index="18" />
		<bit name="Bit 19" index="19" />
		<bit name="Bit 20" index="20" />
		<bit name="Bit 21" index="21" />
		<bit name="Bit 22" index="22" />
		<bit name="Bit 23" index="23" />
		<bit name="Bit 24" index="24" />
		<bit name="Bit 25" index="25" />
		<bit name="Bit 26" index="26" />
		<bit name="Bit 27" index="27" />
		<bit name="Bit 28" index="28" />
		<bit name="Bit 29" index="29" />
		<bit name="Bit 30" index="30" />
		<bit name="Bit 31" index="31" />
	</flags32>
	<int32 name="Unknown" offset="0x4" visible="false" />
	<float32 name="Unknown" offset="0x8" visible="false" />
	<undefined name="Unknown" offset="0xC" visible="false" />
	<float32 name="Unknown" offset="0x10" visible="false" />
	<int8 name="Unknown" offset="0x14" visible="false" />
	<int8 name="Unknown" offset="0x15" visible="false" />
	<int8 name="Unknown" offset="0x16" visible="false" />
	<int8 name="Unknown" offset="0x17" visible="false" />
	<int16 name="Unknown" offset="0x18" visible="false" />
	<int16 name="Unknown" offset="0x1A" visible="false" />
	<undefined name="Unknown" offset="0x1C" visible="false" />
	<tagblock name="Locations" offset="0x20" visible="true" elementSize="0x8">
		<stringId name="Marker Name" offset="0x0" visible="true" />
		<int8 name="Unknown" offset="0x4" visible="false" />
		<int8 name="Unknown" offset="0x5" visible="false" />
		<int8 name="Unknown" offset="0x6" visible="false" />
		<int8 name="Unknown" offset="0x7" visible="false" />
	</tagblock>
	<tagblock name="Events" offset="0x2C" visible="true" elementSize="0x40">
		<stringid name="Name" offset="0x0" visible="true" />
		<int8 name="Unknown" offset="0x4" visible="false" />
		<int8 name="Unknown" offset="0x5" visible="false" />
		<int8 name="Unknown" offset="0x6" visible="false" />
		<int8 name="Unknown" offset="0x7" visible="false" />
		<float32 name="Skip Fraction" offset="0x8" visible="true" />
		<float32 name="Delay Bounds min" offset="0xC" visible="true" />
		<float32 name="Delay Bounds max" offset="0x10" visible="true" />
		<float32 name="Duration Bounds min" offset="0x14" visible="true" />
		<float32 name="Duration Bounds max" offset="0x18" visible="true" />
		<tagblock name="Parts" offset="0x1C" visible="true" elementSize="0x60">
			<enum16 name="Create In Environment" offset="0x0" visible="true">
				<option name="Any Environment" value="0x0" />
				<option name="Air Only" value="0x1" />
				<option name="Water Only" value="0x2" />
				<option name="Space Only" value="0x3" />
			</enum16>
			<enum16 name="Create In Disposition" offset="0x2" visible="true">
				<option name="Either Mode" value="0x0" />
				<option name="Violent Mode Only" value="0x1" />
				<option name="Nonviolent Mode Only" value="0x2" />
			</enum16>
			<int16 name="Location Index" offset="0x4" visible="true" />
			<int16 name="Unknown" offset="0x6" visible="false" />
			<int16 name="Unknown" offset="0x8" visible="false" />
			<int8 name="Unknown" offset="0xA" visible="false" />
			<enum8 name="Camera Mode" offset="0xB" visible="true">
				<option name="Independent Of Camera Mode" value="0x0" />
				<option name="First Person Only" value="0x1" />
				<option name="Third Person Only" value="0x2" />
				<option name="Both First And Third" value="0x3" />
			</enum8>
			<enum32 name="Runtime Base Group Tag" offset="0xC" visible="true" tooltip="This should be set to match the below &quot;Type&quot; tag reference, any object should use &quot;object&quot;.">
				<option name="beam - beam_system" value="0x6265616D" />
				<option name="char - character" value="0x63686172" />
				<option name="cntl - contrail_system" value="0x636E746C" />
				<option name="cpem - cheap_particle_emitter" value="0x6370656D" />
				<option name="decs - decal_system" value="0x64656373" />
				<option name="drdf - damage_response_definition" value="0x64726466" />
				<option name="gldf - cheap_light" value="0x676C6466" />
				<option name="jpt! - damage_effect" value="0x6A707421" />
				<option name="lens - lens_flare" value="0x6C656E73" />
				<option name="ligh - light" value="0x6C696768" />
				<option name="ltvl - light_volume_system" value="0x6C74766C" />
				<option name="obje - object" value="0x6F626A65" />
				<option name="rwrd - render_water_ripple" value="0x72777264" />
				<option name="sefc - area_screen_effect" value="0x73656663" />
				<option name="shit - shield_impact" value="0x73686974" />
				<option name="snd! - sound" value="0x736E6421" />
			</enum32>
			<tagRef name="Type" offset="0x10" visible="true" tooltip="The above &quot;Runtime Base Group Tag&quot; field should match this reference." />
			<float32 name="Velocity Bounds min" offset="0x20" visible="true" />
			<float32 name="Velocity Bounds max" offset="0x24" visible="true" />
			<undefined name="Unknown" offset="0x28" visible="false" />
			<undefined name="Unknown" offset="0x2C" visible="false" />
			<degree name="Velocity Cone Angle" offset="0x30" visible="true" />
			<degree name="Angular Velocity Bounds min" offset="0x34" visible="true" />
			<degree name="Angular Velocity Bounds max" offset="0x38" visible="true" />
			<float32 name="Radius Modifier Bounds min" offset="0x3C" visible="true" />
			<float32 name="Radius Modifier Bounds max" offset="0x40" visible="true" />
			<float32 name="Origin Offset X" offset="0x44" visible="true" />
			<float32 name="Origin Offset Y" offset="0x48" visible="true" />
			<float32 name="Origin Offset Z" offset="0x4C" visible="true" />
			<degree name="Origin Rotation i" offset="0x50" visible="true" />
			<degree name="Origin Rotation j" offset="0x54" visible="true" />
			<flags32 name="A Scales Values" offset="0x58" visible="true">
				<bit name="Bit 0" index="0" />
				<bit name="Bit 1" index="1" />
				<bit name="Bit 2" index="2" />
				<bit name="Bit 3" index="3" />
				<bit name="Bit 4" index="4" />
				<bit name="Bit 5" index="5" />
				<bit name="Bit 6" index="6" />
				<bit name="Bit 7" index="7" />
				<bit name="Bit 8" index="8" />
				<bit name="Bit 9" index="9" />
				<bit name="Bit 10" index="10" />
				<bit name="Bit 11" index="11" />
				<bit name="Bit 12" index="12" />
				<bit name="Bit 13" index="13" />
				<bit name="Bit 14" index="14" />
				<bit name="Bit 15" index="15" />
				<bit name="Bit 16" index="16" />
				<bit name="Bit 17" index="17" />
				<bit name="Bit 18" index="18" />
				<bit name="Bit 19" index="19" />
				<bit name="Bit 20" index="20" />
				<bit name="Bit 21" index="21" />
				<bit name="Bit 22" index="22" />
				<bit name="Bit 23" index="23" />
				<bit name="Bit 24" index="24" />
				<bit name="Bit 25" index="25" />
				<bit name="Bit 26" index="26" />
				<bit name="Bit 27" index="27" />
				<bit name="Bit 28" index="28" />
				<bit name="Bit 29" index="29" />
				<bit name="Bit 30" index="30" />
				<bit name="Bit 31" index="31" />
			</flags32>
			<flags32 name="B Scales Values" offset="0x5C" visible="true">
				<bit name="Bit 0" index="0" />
				<bit name="Bit 1" index="1" />
				<bit name="Bit 2" index="2" />
				<bit name="Bit 3" index="3" />
				<bit name="Bit 4" index="4" />
				<bit name="Bit 5" index="5" />
				<bit name="Bit 6" index="6" />
				<bit name="Bit 7" index="7" />
				<bit name="Bit 8" index="8" />
				<bit name="Bit 9" index="9" />
				<bit name="Bit 10" index="10" />
				<bit name="Bit 11" index="11" />
				<bit name="Bit 12" index="12" />
				<bit name="Bit 13" index="13" />
				<bit name="Bit 14" index="14" />
				<bit name="Bit 15" index="15" />
				<bit name="Bit 16" index="16" />
				<bit name="Bit 17" index="17" />
				<bit name="Bit 18" index="18" />
				<bit name="Bit 19" index="19" />
				<bit name="Bit 20" index="20" />
				<bit name="Bit 21" index="21" />
				<bit name="Bit 22" index="22" />
				<bit name="Bit 23" index="23" />
				<bit name="Bit 24" index="24" />
				<bit name="Bit 25" index="25" />
				<bit name="Bit 26" index="26" />
				<bit name="Bit 27" index="27" />
				<bit name="Bit 28" index="28" />
				<bit name="Bit 29" index="29" />
				<bit name="Bit 30" index="30" />
				<bit name="Bit 31" index="31" />
			</flags32>
		</tagblock>
		<tagblock name="Accelerations" offset="0x28" visible="true" elementSize="0x14">
			<enum16 name="Create In Environment" offset="0x0" visible="true">
				<option name="Any Environment" value="0x0" />
				<option name="Air Only" value="0x1" />
				<option name="Water Only" value="0x2" />
				<option name="Space Only" value="0x3" />
			</enum16>
			<enum16 name="Create In Disposition" offset="0x2" visible="true">
				<option name="Either Mode" value="0x0" />
				<option name="Violent Mode Only" value="0x1" />
				<option name="Nonviolent Mode Only" value="0x2" />
			</enum16>
			<int16 name="Location Index" offset="0x4" visible="true" />
			<int16 name="Unknown" offset="0x6" visible="false" />
			<float32 name="Acceleration" offset="0x8" visible="true" />
			<float32 name="Inner Cone Angle" offset="0xC" visible="true" />
			<float32 name="Outer Cone Angle" offset="0x10" visible="true" />
		</tagblock>
		<tagblock name="Particle Systems" offset="0x34" visible="true" elementSize="0x68">
			<int8 name="Unknown" offset="0x0" visible="false" />
			<int8 name="Unknown" offset="0x1" visible="false" />
			<int8 name="Unknown" offset="0x2" visible="false" />
			<int8 name="Unknown" offset="0x3" visible="false" />
			<tagRef name="Particle" offset="0x4" visible="true" />
			<int16 name="Unknown" offset="0x14" visible="false" />
			<int16 name="Location Index" offset="0x16" visible="true" />
			<enum16 name="Coordinate System" offset="0x18" visible="true">
				<option name="World" value="0x0" />
				<option name="Local" value="0x1" />
				<option name="Parent" value="0x2" />
			</enum16>
			<enum16 name="Environment" offset="0x1A" visible="true">
				<option name="Any Environment" value="0x0" />
				<option name="Air Only" value="0x1" />
				<option name="Water Only" value="0x2" />
				<option name="Space Only" value="0x3" />
			</enum16>
			<enum16 name="Disposition" offset="0x1C" visible="true">
				<option name="Either Mode" value="0x0" />
				<option name="Violent Mode Only" value="0x1" />
				<option name="Nonviolent Mode Only" value="0x2" />
			</enum16>
			<enum16 name="Camera Mode" offset="0x1E" visible="true">
				<option name="Independent Of Camera Mode" value="0x0" />
				<option name="First Person Only" value="0x1" />
				<option name="Third Person Only" value="0x2" />
				<option name="Both First And Third" value="0x3" />
			</enum16>
			<int16 name="Sort Bias" offset="0x20" visible="true" />
			<flags16 name="Flags" offset="0x22" visible="true">
				<bit name="Bit 0" index="0" />
				<bit name="Bit 1" index="1" />
				<bit name="Bit 2" index="2" />
				<bit name="Bit 3" index="3" />
				<bit name="Bit 4" index="4" />
				<bit name="Bit 5" index="5" />
				<bit name="Bit 6" index="6" />
				<bit name="Bit 7" index="7" />
				<bit name="Bit 8" index="8" />
				<bit name="Bit 9" index="9" />
				<bit name="Bit 10" index="10" />
				<bit name="Bit 11" index="11" />
				<bit name="Bit 12" index="12" />
				<bit name="Bit 13" index="13" />
				<bit name="Bit 14" index="14" />
				<bit name="Bit 15" index="15" />
			</flags16>
			<int16 name="Unknown" offset="0x24" visible="false" />
			<int16 name="Unknown" offset="0x26" visible="false" />
			<undefined name="Unknown" offset="0x28" visible="false" />
			<undefined name="Unknown" offset="0x2C" visible="false" />
			<undefined name="Unknown" offset="0x30" visible="false" />
			<undefined name="Unknown" offset="0x34" visible="false" />
			<undefined name="Unknown" offset="0x38" visible="false" />
			<undefined name="Unknown" offset="0x3C" visible="false" />
			<undefined name="Unknown" offset="0x40" visible="false" />
			<undefined name="Unknown" offset="0x44" visible="false" />
			<float32 name="Amount/Size" offset="0x48" visible="true" />
			<float32 name="LOD Out Distance" offset="0x4C" visible="true" />
			<float32 name="LOD Feather Out Delta" offset="0x50" visible="true" />
			<float32 name="Inverse LOD Feather Out" offset="0x54" visible="true" />
			<tagblock name="Emitters" offset="0x58" visible="true" elementSize="0x330">
				<stringid name="Name" offset="0x0" visible="true" />
				<flags16 name="Unknown" offset="0x4" visible="true">
					<bit name="Bit 0" index="0" />
					<bit name="Bit 1" index="1" />
					<bit name="Bit 2" index="2" />
					<bit name="Bit 3" index="3" />
					<bit name="Bit 4" index="4" />
					<bit name="Bit 5" index="5" />
					<bit name="Bit 6" index="6" />
					<bit name="Bit 7" index="7" />
					<bit name="Bit 8" index="8" />
					<bit name="Bit 9" index="9" />
					<bit name="Bit 10" index="10" />
					<bit name="Bit 11" index="11" />
					<bit name="Bit 12" index="12" />
					<bit name="Bit 13" index="13" />
					<bit name="Bit 14" index="14" />
					<bit name="Bit 15" index="15" />
				</flags16>
				<int16 name="Unknown" offset="0x6" visible="false" />
				<undefined name="Unknown" offset="0x8" visible="false" />
				<tagRef name="Custom Emitter Points" offset="0xC" visible="true" />
				<tagRef name="Unknown" offset="0x1C" visible="true" />
				<undefined name="Unknown" offset="0x2C" visible="false" />
				<undefined name="Unknown" offset="0x30" visible="false" />
				<undefined name="Unknown" offset="0x34" visible="false" />
				<undefined name="Unknown" offset="0x38" visible="false" />
				<undefined name="Unknown" offset="0x3C" visible="false" />
				<undefined name="Unknown" offset="0x40" visible="false" />
				<undefined name="Unknown" offset="0x44" visible="false" />
				<int8 name="Input" offset="0x48" visible="true" />
				<int8 name="Input Range" offset="0x49" visible="true" />
				<enum8 name="Output Kind" offset="0x4A" visible="true">
					<option name="None" value="0x0" />
					<option name="Plus" value="0x1" />
					<option name="Times" value="0x2" />
				</enum8>
				<int8 name="Output" offset="0x4B" visible="true" />
				<dataRef name="Unknown" offset="0x4C" visible="true" />
				<undefined name="Unknown" offset="0x60" visible="false" />
				<undefined name="Unknown" offset="0x64" visible="false" />
				<undefined name="Unknown" offset="0x68" visible="false" />
				<undefined name="Unknown" offset="0x6C" visible="false" />
				<undefined name="Unknown" offset="0x70" visible="false" />
				<undefined name="Unknown" offset="0x74" visible="false" />
				<undefined name="Unknown" offset="0x78" visible="false" />
				<undefined name="Unknown" offset="0x7C" visible="false" />
				<int8 name="Input" offset="0x80" visible="true" />
				<int8 name="Input Range" offset="0x81" visible="true" />
				<enum8 name="Output Kind" offset="0x82" visible="true">
					<option name="None" value="0x0" />
					<option name="Plus" value="0x1" />
					<option name="Times" value="0x2" />
				</enum8>
				<int8 name="Output" offset="0x83" visible="true" />
				<dataref name="Unknown" offset="0x84" visible="true" />
				<undefined name="Unknown" offset="0x98" visible="false" />
				<undefined name="Unknown" offset="0x9C" visible="false" />
				<undefined name="Unknown" offset="0xA0" visible="false" />
				<undefined name="Unknown" offset="0xA4" visible="false" />
				<undefined name="Unknown" offset="0xA8" visible="false" />
				<undefined name="Unknown" offset="0xAC" visible="false" />
				<undefined name="Unknown" offset="0xB0" visible="false" />
				<undefined name="Unknown" offset="0xB4" visible="false" />
				<int8 name="Input" offset="0xB8" visible="true" />
				<int8 name="Input Range" offset="0xB9" visible="true" />
				<enum8 name="Output Kind" offset="0xBA" visible="true">
					<option name="None" value="0x0" />
					<option name="Plus" value="0x1" />
					<option name="Times" value="0x2" />
				</enum8>
				<int8 name="Output" offset="0xBB" visible="true" />
				<dataref name="Unknown" offset="0xBC" visible="true" />
				<undefined name="Unknown" offset="0xD0" visible="false" />
				<undefined name="Unknown" offset="0xD4" visible="false" />
				<int8 name="Input" offset="0xD8" visible="true" />
				<int8 name="Input Range" offset="0xD9" visible="true" />
				<enum8 name="Output Kind" offset="0xDA" visible="true">
					<option name="None" value="0x0" />
					<option name="Plus" value="0x1" />
					<option name="Times" value="0x2" />
				</enum8>
				<int8 name="Output" offset="0xDB" visible="true" />
				<dataref name="Unknown" offset="0xDC" visible="true" />
				<undefined name="Unknown" offset="0xF0" visible="false" />
				<undefined name="Unknown" offset="0xF4" visible="false" />
				<int8 name="Input" offset="0xF8" visible="true" />
				<int8 name="Input Range" offset="0xF9" visible="true" />
				<enum8 name="Output Kind" offset="0xFA" visible="true">
					<option name="None" value="0x0" />
					<option name="Plus" value="0x1" />
					<option name="Times" value="0x2" />
				</enum8>
				<int8 name="Output" offset="0xFB" visible="true" />
				<dataref name="Unknown" offset="0xFC" visible="true" />
				<undefined name="Unknown" offset="0x110" visible="false" />
				<undefined name="Unknown" offset="0x114" visible="false" />
				<int8 name="Input" offset="0x118" visible="true" />
				<int8 name="Input Range" offset="0x119" visible="true" />
				<enum8 name="Output Kind" offset="0x11A" visible="true">
					<option name="None" value="0x0" />
					<option name="Plus" value="0x1" />
					<option name="Times" value="0x2" />
				</enum8>
				<int8 name="Output" offset="0x11B" visible="true" />
				<dataref name="Unknown" offset="0x11C" visible="true" />
				<undefined name="Unknown" offset="0x130" visible="false" />
				<undefined name="Unknown" offset="0x134" visible="false" />
				<int8 name="Input" offset="0x138" visible="true" />
				<int8 name="Input Range" offset="0x139" visible="true" />
				<enum8 name="Output Kind" offset="0x13A" visible="true">
					<option name="None" value="0x0" />
					<option name="Plus" value="0x1" />
					<option name="Times" value="0x2" />
				</enum8>
				<int8 name="Output" offset="0x13B" visible="true" />
				<dataref name="Unknown" offset="0x13C" visible="true" />
				<undefined name="Unknown" offset="0x150" visible="false" />
				<undefined name="Unknown" offset="0x154" visible="false" />
				<int8 name="Input" offset="0x158" visible="true" />
				<int8 name="Input Range" offset="0x159" visible="true" />
				<enum8 name="Output Kind" offset="0x15A" visible="true">
					<option name="None" value="0x0" />
					<option name="Plus" value="0x1" />
					<option name="Times" value="0x2" />
				</enum8>
				<int8 name="Output" offset="0x15B" visible="true" />
				<dataref name="Unknown" offset="0x15C" visible="true" />
				<undefined name="Unknown" offset="0x170" visible="false" />
				<undefined name="Unknown" offset="0x174" visible="false" />
				<int8 name="Input" offset="0x178" visible="true" />
				<int8 name="Input Range" offset="0x179" visible="true" />
				<enum8 name="Output Kind" offset="0x17A" visible="true">
					<option name="None" value="0x0" />
					<option name="Plus" value="0x1" />
					<option name="Times" value="0x2" />
				</enum8>
				<int8 name="Output" offset="0x17B" visible="true" />
				<dataref name="Unknown" offset="0x17C" visible="true" />
				<undefined name="Unknown" offset="0x190" visible="false" />
				<undefined name="Unknown" offset="0x194" visible="false" />
				<tagref name="Particle Physics" offset="0x198" visible="true" />
				<undefined name="Unknown" offset="0x1A8" visible="false" />
				<tagblock name="Unknown" offset="0x1AC" visible="false" elementSize="0x18">
					<int32 name="Unknown" offset="0x0" visible="false" />
					<tagblock name="Unknown" offset="0x4" visible="false" elementSize="0x24">
						<undefined name="Unknown" offset="0x0" visible="false" />
						<int8 name="Input" offset="0x4" visible="true" />
						<int8 name="Input Range" offset="0x5" visible="true" />
						<enum8 name="Output Kind" offset="0x6" visible="true">
							<option name="None" value="0x0" />
							<option name="Plus" value="0x1" />
							<option name="Times" value="0x2" />
						</enum8>
						<int8 name="Output" offset="0x7" visible="true" />
						<dataRef name="Unknown" offset="0x8" visible="true" />
						<undefined name="Unknown" offset="0x1C" visible="false" />
						<undefined name="Unknown" offset="0x20" visible="false" />
					</tagblock>
					<undefined name="Unknown" offset="0x10" visible="false" />
					<undefined name="Unknown" offset="0x14" visible="false" />
				</tagblock>
				<tagref name="Displacement Map" offset="0x1B8" visible="true" />
				<int8 name="Input" offset="0x1C8" visible="true" />
				<int8 name="Input Range" offset="0x1C9" visible="true" />
				<enum8 name="Output Kind" offset="0x1CA" visible="true">
					<option name="None" value="0x0" />
					<option name="Plus" value="0x1" />
					<option name="Times" value="0x2" />
				</enum8>
				<int8 name="Output" offset="0x1CB" visible="true" />
				<dataref name="Unknown" offset="0x1CC" visible="true" />
				<undefined name="Unknown" offset="0x1E0" visible="false" />
				<undefined name="Unknown" offset="0x1E4" visible="false" />
				<undefined name="Unknown" offset="0x1E8" visible="false" />
				<undefined name="Unknown" offset="0x1EC" visible="false" />
				<undefined name="Unknown" offset="0x1F0" visible="false" />
				<undefined name="Unknown" offset="0x1F4" visible="false" />
				<undefined name="Unknown" offset="0x1F8" visible="false" />
				<undefined name="Unknown" offset="0x1FC" visible="false" />
				<int8 name="Input" offset="0x200" visible="true" />
				<int8 name="Input Range" offset="0x201" visible="true" />
				<enum8 name="Output Kind" offset="0x202" visible="true">
					<option name="None" value="0x0" />
					<option name="Plus" value="0x1" />
					<option name="Times" value="0x2" />
				</enum8>
				<int8 name="Output" offset="0x203" visible="true" />
				<dataref name="Unknown" offset="0x204" visible="true" />
				<undefined name="Unknown" offset="0x218" visible="false" />
				<undefined name="Unknown" offset="0x21C" visible="false" />
				<int8 name="Input" offset="0x220" visible="true" />
				<int8 name="Input Range" offset="0x221" visible="true" />
				<enum8 name="Output Kind" offset="0x222" visible="true">
					<option name="None" value="0x0" />
					<option name="Plus" value="0x1" />
					<option name="Times" value="0x2" />
				</enum8>
				<int8 name="Output" offset="0x223" visible="true" />
				<dataref name="Unknown" offset="0x224" visible="true" />
				<undefined name="Unknown" offset="0x238" visible="false" />
				<undefined name="Unknown" offset="0x23C" visible="false" />
				<int8 name="Input" offset="0x240" visible="true" />
				<int8 name="Input Range" offset="0x241" visible="true" />
				<enum8 name="Output Kind" offset="0x242" visible="true">
					<option name="None" value="0x0" />
					<option name="Plus" value="0x1" />
					<option name="Times" value="0x2" />
				</enum8>
				<int8 name="Output" offset="0x243" visible="true" />
				<dataref name="Unknown" offset="0x244" visible="true" />
				<undefined name="Unknown" offset="0x258" visible="false" />
				<undefined name="Unknown" offset="0x25C" visible="false" />
				<int8 name="Input" offset="0x260" visible="true" />
				<int8 name="Input Range" offset="0x261" visible="true" />
				<enum8 name="Output Kind" offset="0x262" visible="true">
					<option name="None" value="0x0" />
					<option name="Plus" value="0x1" />
					<option name="Times" value="0x2" />
				</enum8>
				<int8 name="Output" offset="0x263" visible="true" />
				<dataref name="Unknown" offset="0x264" visible="true" />
				<undefined name="Unknown" offset="0x278" visible="false" />
				<undefined name="Unknown" offset="0x27C" visible="false" />
				<int8 name="Input" offset="0x280" visible="true" />
				<int8 name="Input Range" offset="0x281" visible="true" />
				<enum8 name="Output Kind" offset="0x282" visible="true">
					<option name="None" value="0x0" />
					<option name="Plus" value="0x1" />
					<option name="Times" value="0x2" />
				</enum8>
				<int8 name="Output" offset="0x283" visible="true" />
				<dataref name="Particle Scale" offset="0x284" visible="true" />
				<undefined name="Unknown" offset="0x298" visible="false" />
				<undefined name="Unknown" offset="0x29C" visible="false" />
				<int8 name="Input" offset="0x2A0" visible="true" />
				<int8 name="Input Range" offset="0x2A1" visible="true" />
				<enum8 name="Output Kind" offset="0x2A2" visible="true">
					<option name="None" value="0x0" />
					<option name="Plus" value="0x1" />
					<option name="Times" value="0x2" />
				</enum8>
				<int8 name="Output" offset="0x2A3" visible="true" />
				<dataref name="Particle Tint" offset="0x2A4" visible="true" />
				<undefined name="Unknown" offset="0x2B8" visible="false" />
				<undefined name="Unknown" offset="0x2BC" visible="false" />
				<int8 name="Input" offset="0x2C0" visible="true" />
				<int8 name="Input Range" offset="0x2C1" visible="true" />
				<enum8 name="Output Kind" offset="0x2C2" visible="true">
					<option name="None" value="0x0" />
					<option name="Plus" value="0x1" />
					<option name="Times" value="0x2" />
				</enum8>
				<int8 name="Output" offset="0x2C3" visible="true" />
				<dataref name="Particle Alpha" offset="0x2C4" visible="true" />
				<undefined name="Unknown" offset="0x2D8" visible="false" />
				<undefined name="Unknown" offset="0x2DC" visible="false" />
				<int8 name="Input" offset="0x2E0" visible="true" />
				<int8 name="Input Range" offset="0x2E1" visible="true" />
				<enum8 name="Output Kind" offset="0x2E2" visible="true">
					<option name="None" value="0x0" />
					<option name="Plus" value="0x1" />
					<option name="Times" value="0x2" />
				</enum8>
				<int8 name="Output" offset="0x2E3" visible="true" />
				<dataref name="Particle Alpha Black Point" offset="0x2E4" visible="true" />
				<undefined name="Unknown" offset="0x2F8" visible="false" />
				<undefined name="Unknown" offset="0x2FC" visible="false" />
				<int32 name="Unknown" offset="0x300" visible="false" />
				<int32 name="Unknown" offset="0x304" visible="false" />
				<int32 name="Unknown" offset="0x308" visible="false" />
				<tagblock name="Unknown" offset="0x30C" visible="false" elementSize="0x10" align="0x10">
					<undefined name="Unknown" offset="0x0" visible="false" />
					<undefined name="Unknown" offset="0x4" visible="false" />
					<undefined name="Unknown" offset="0x8" visible="false" />
					<undefined name="Unknown" offset="0xC" visible="false" />
				</tagblock>
				<tagblock name="Compiled Functions" offset="0x318" visible="false" elementSize="0x40" align="0x10">
					<float32 name="Unknown" offset="0x0" visible="true" />
					<float32 name="Unknown" offset="0x4" visible="true" />
					<float32 name="Feather Amount" offset="0x8" visible="true" />
					<float32 name="Scale" offset="0xC" visible="true" />
					<float32 name="Unknown" offset="0x10" visible="true" />
					<float32 name="Unknown" offset="0x14" visible="true" />
					<float32 name="Unknown" offset="0x18" visible="true" />
					<undefined name="Unknown" offset="0x1C" visible="true" />
					<float32 name="Unknown" offset="0x20" visible="true" />
					<float32 name="Unknown" offset="0x24" visible="true" />
					<float32 name="Unknown" offset="0x28" visible="true" />
					<float32 name="Unknown" offset="0x2C" visible="true" />
					<undefined name="Unknown" offset="0x30" visible="true" />
					<float32 name="Unknown" offset="0x34" visible="true" />
					<float32 name="Unknown" offset="0x38" visible="true" />
					<undefined name="Unknown" offset="0x3C" visible="true" />
				</tagblock>
				<tagblock name="Compiled Color Functions" offset="0x324" visible="true" elementSize="0x10" align="0x10">
					<float32 name="Red" offset="0x0" visible="true" />
					<float32 name="Green" offset="0x4" visible="true" />
					<float32 name="Blue" offset="0x8" visible="true" />
					<float32 name="Magnitude" offset="0xC" visible="true" />
				</tagblock>
			</tagblock>
			<undefined name="Unknown" offset="0x64" visible="false" />
		</tagblock>
	</tagblock>
	<tagRef name="Looping Sound" offset="0x38" visible="true" />
	<int8 name="Location Index" offset="0x48" visible="true" />
	<int8 name="Bind Scale To Event Index" offset="0x49" visible="true" />
	<int16 name="Local Location 1" offset="0x4A" visible="true" />
	<float32 name="Always Play Distance" offset="0x4C" visible="true" />
	<float32 name="Never Play Distance" offset="0x50" visible="true" />
	<float32 name="Runtime Lightprobe Death Delay" offset="0x54" visible="true" />
	<float32 name="Runtime Local Space Death Delay" offset="0x58" visible="true" />
	<tagblock name="Conical Distribution" offset="0x5C" visible="true" elementSize="0xC">
		<comment title="Conical Projection">projectile_count = yaw_count*pitch_count</comment>
		<int16 name="Yaw Count" offset="0x0" visible="true" />
		<int16 name="Pitch Count" offset="0x2" visible="true" />
		<float32 name="Distribution Exponent" offset="0x4" visible="true" tooltip="exp==.5 even distribution, exp&gt;.5== tighter" />
		<degree name="Spread" offset="0x8" visible="true" tooltip="degrees" />
	</tagblock>
</plugin>